botframe/__init__.py
botframe/vk_bot.py
botframe-0.0a4.dist-info/LICENSE
botframe-0.0a4.dist-info/METADATA
botframe-0.0a4.dist-info/WHEEL
botframe-0.0a4.dist-info/top_level.txt
botframe-0.0a4.dist-info/RECORD
