Metadata-Version: 2.1
Name: botframe
Version: 0.0a4
Summary: Bot framework for Vk.com
Home-page: https://github.com/Waika28/botframe
Author: Eugene-Rybin
Author-email: z.ribin20@gmail.com
License: UNKNOWN
Platform: UNKNOWN
Classifier: Development Status :: 3 - Alpha
Classifier: Programming Language :: Python :: 3
Classifier: License :: OSI Approved :: GNU General Public License v3 (GPLv3)
Classifier: Operating System :: OS Independent
Requires-Python: >=3.6
Requires-Dist: vk-api (>=11.8.0)
